<?xml version="1.0" encoding="UTF-8"?>

<asset name="Bird.jpg" id="AUylhVc8OlsiThKd8lIK">
  <category id="users_201504_e7_bab83ede1"/>
  <property name="assetmodificationdate">2015-04-10T22:48:41.000Z</property>
  <property name="colortype">3</property>
  <property name="isfolder">true</property>
  <property name="importstatus">complete</property>
  <property name="longcaption">Flight and song.</property>
  <property name="previewstatus">2</property>
  <property name="assetviews">1</property>
  <property name="assetaddeddate">2015-04-10T22:48:41.000Z</property>
  <property name="height">836</property>
  <property name="namesorted">Bird.jpg</property>
  <property name="shoppingcarttarget">false</property>
  <property name="primaryfile">Bird.jpg</property>
  <property name="description">AUylhVc8OlsiThKd8lIK Bird.jpg bab83ede1 admin Flight and song. users_201504_e7_bab83ede1 Index users e7 201504 bab83ede1 users 201504 e7 bab83ede1</property>
  <property name="assetcreationdate">2011-07-18T17:48:17.000Z</property>
  <property name="length">0</property>
  <property name="viewasset">group_administrators | true | user_admin</property>
  <property name="catalogid">qa/catalog</property>
  <property name="assettype">photo</property>
  <property name="previewtatus">0</property>
  <property name="bitspersample">8</property>
  <property name="fileformat">jpg</property>
  <property name="pages">0</property>
  <property name="pushstatus">resend</property>
  <property name="width">1024</property>
  <property name="category-exact">users_201504_e7_bab83ede1</property>
  <property name="publisheds3">false</property>
  <property name="filesize">391869</property>
  <property name="owner">admin</property>
  <property name="datatype">original</property>
  <property name="editstatus">1</property>
  <property name="assetvotes">0</property>
  <property name=".version">3</property>
  <property name="recordmodificationdate">2015-04-10 18:49:00 -0400</property>
</asset>
